working_date/__init__.py
working_date/main.py
working_date-0.4.dist-info/METADATA
working_date-0.4.dist-info/WHEEL
working_date-0.4.dist-info/entry_points.txt
working_date-0.4.dist-info/top_level.txt
working_date-0.4.dist-info/RECORD
