Metadata-Version: 2.2
Name: working_date
Version: 0.4
Requires-Dist: datetime>=5.5
Dynamic: description
Dynamic: description-content-type
Dynamic: requires-dist
